ibridgescontrib/ibridgesdvn/__init__.py
ibridgescontrib/ibridgesdvn/dataverse.py
ibridgescontrib/ibridgesdvn/ds_meta.py
ibridgescontrib/ibridgesdvn/dvn_config.py
ibridgescontrib/ibridgesdvn/dvn_dataset_commands.py
ibridgescontrib/ibridgesdvn/dvn_init.py
ibridgescontrib/ibridgesdvn/dvn_operations.py
ibridgescontrib/ibridgesdvn/dvn_setup.py
ibridgescontrib/ibridgesdvn/json_templates.py
ibridgescontrib/ibridgesdvn/utils.py
ibridgescontrib/ibridgesdvn/gui/gui_dataverse.py
ibridgescontrib/ibridgesdvn/gui/gui_popup_widgets.py
ibridgescontrib/ibridgesdvn/gui/gui_thread.py
ibridgescontrib/ibridgesdvn/gui/uiCreateDataset.py
ibridgescontrib/ibridgesdvn/gui/uiCreateMetadata.py
ibridgescontrib/ibridgesdvn/gui/uiCreateUrl.py
ibridgescontrib/ibridgesdvn/gui/uiDataverse.py
ibridgescontrib/ibridgesdvn/gui/ui_files/create_dataset.ui
ibridgescontrib/ibridgesdvn/gui/ui_files/create_url.ui
ibridgescontrib/ibridgesdvn/gui/ui_files/metadata_form.ui
ibridgescontrib/ibridgesdvn/gui/ui_files/tabDataverse.ui
ibridgesdvn-1.0.4.dist-info/licenses/LICENSE
ibridgesdvn-1.0.4.dist-info/METADATA
ibridgesdvn-1.0.4.dist-info/WHEEL
ibridgesdvn-1.0.4.dist-info/entry_points.txt
ibridgesdvn-1.0.4.dist-info/top_level.txt
ibridgesdvn-1.0.4.dist-info/RECORD
