Metadata-Version: 2.4
Name: ibridgesdvn
Version: 1.0.4
Summary: iBridges plugin for interacting with Dataverse
Author-email: Christine Staiger <c.staiger@uu.nl>
License:                   GNU LESSER GENERAL PUBLIC LICENSE
Project-URL: GitHub, https://github.com/iBridges-for-iRODS/iBridges
Project-URL: documentation, https://github.com/iBridges-for-iRODS/iBridges
Keywords: irods,data management,storage,dataverse
Classifier: Programming Language :: Python :: 3
Classifier: Programming Language :: Python :: 3.9
Classifier: Programming Language :: Python :: 3.10
Classifier: Programming Language :: Python :: 3.11
Classifier: Programming Language :: Python :: 3.12
Classifier: Programming Language :: Python :: 3.13
Classifier: Development Status :: 5 - Production/Stable
Classifier: License :: OSI Approved :: MIT License
Requires-Python: >=3.8
License-File: LICENSE
Requires-Dist: ibridges<2.1,>=2.0.0
Requires-Dist: pyDataverse
Requires-Dist: httpx
Provides-Extra: gui
Requires-Dist: ibridgesgui<3.0.0,>=2.0.0; extra == "gui"
Provides-Extra: test
Requires-Dist: pylint; extra == "test"
Requires-Dist: pytest; extra == "test"
Requires-Dist: pytest-cov; extra == "test"
Requires-Dist: ruff; extra == "test"
Requires-Dist: mypy; extra == "test"
Requires-Dist: types-tqdm; extra == "test"
Dynamic: license-file
